fragapy/__init__.py
fragapy/appsettings.py
fragapy/importlib.py
fragapy/admin/__init__.py
fragapy/admin/adminparts.py
fragapy/admin/changelist.py
fragapy/admin/filterspecs.py
fragapy/admin/inline.py
fragapy/admin/adminhelp/__init__.py
fragapy/admin/adminhelp/admin.py
fragapy/admin/adminhelp/models.py
fragapy/admin/adminhelp/tests.py
fragapy/admin/adminhelp/urls.py
fragapy/admin/adminhelp/views.py
fragapy/admin/adminhelp/templatetags/__init__.py
fragapy/admin/adminhelp/templatetags/help.py
fragapy/amazon/__init__.py
fragapy/amazon/msgbody.txt
fragapy/amazon/ses-get-stats.pl
fragapy/amazon/ses-send-email.pl
fragapy/amazon/ses-verify-email-address.pl
fragapy/amazon/smtp_relay.py
fragapy/amazon/smtp_relay.sh
fragapy/amazon/smtpreldaemon.cfg
fragapy/amazon/smtpreldaemon.py
fragapy/auth/__init__.py
fragapy/auth/middleware.py
fragapy/cloneable_models/__init__.py
fragapy/cloneable_models/exceptions.py
fragapy/cloneable_models/models.py
fragapy/cloneable_models/utils.py
fragapy/common/__init__.py
fragapy/common/context_processors.py
fragapy/common/middleware.py
fragapy/common/algorithms/__init__.py
fragapy/common/algorithms/dictdifference.py
fragapy/common/algorithms/mergesort.py
fragapy/common/encoding/__init__.py
fragapy/common/encoding/guess.py
fragapy/common/models/__init__.py
fragapy/common/models/adminlink.py
fragapy/common/templatetags/__init__.py
fragapy/common/templatetags/macros.py
fragapy/countries/__init__.py
fragapy/countries/forms.py
fragapy/currencies/__init__.py
fragapy/currencies/admin.py
fragapy/currencies/context_processors.py
fragapy/currencies/fields.py
fragapy/currencies/models.py
fragapy/currencies/urls.py
fragapy/currencies/utils.py
fragapy/currencies/views.py
fragapy/currencies/templatetags/__init__.py
fragapy/currencies/templatetags/currency.py
fragapy/currencies/tests/__init__.py
fragapy/currencies/tests/settings.py
fragapy/currencies/tests/tests.py
fragapy/cz_localflavour/__init__.py
fragapy-1.3.0.dist-info/METADATA
fragapy-1.3.0.dist-info/RECORD
fragapy-1.3.0.dist-info/WHEEL
fragapy-1.3.0.dist-info/top_level.txt
