Metadata-Version: 2.1
Name: fragapy
Version: 1.3.0
Summary: Fragaria commons library
Home-page: https://github.com/fragaria/fragapy
Author: Fragaria s.r.o
Author-email: admin@fragaria.cz
License: BSD
Platform: UNKNOWN
Classifier: License :: OSI Approved :: BSD License
Classifier: Development Status :: 4 - Beta
Classifier: Environment :: Web Environment
Classifier: Intended Audience :: Developers
Classifier: Operating System :: OS Independent
Classifier: Programming Language :: Python
Classifier: Framework :: Django
Classifier: Topic :: Software Development :: Libraries :: Python Modules
Requires-Dist: django-positions (==0.4.3)
